sim_csv_script/__init__.py
sim_csv_script/__main__.py
sim_csv_script/app.py
sim_csv_script/csv_utils.py
sim_csv_script-1.4.0.dist-info/METADATA
sim_csv_script-1.4.0.dist-info/WHEEL
sim_csv_script-1.4.0.dist-info/entry_points.txt
sim_csv_script-1.4.0.dist-info/pbr.json
sim_csv_script-1.4.0.dist-info/top_level.txt
sim_csv_script-1.4.0.dist-info/RECORD
