Metadata-Version: 2.1
Name: sim-csv-script
Version: 1.4.0
Summary: Program SIM cards by importing CSV file
Home-page: UNKNOWN
Author: Andrew Ma
License: UNKNOWN
Platform: any
Classifier: Programming Language :: Python :: 3.6
Classifier: Programming Language :: Python :: 3.7
Classifier: Programming Language :: Python :: 3.8
Classifier: Programming Language :: Python :: 3.9
Classifier: Programming Language :: Python :: 3 :: Only
Classifier: Operating System :: OS Independent
Classifier: Topic :: System :: Hardware :: Universal Serial Bus (USB) :: Smart Card
Classifier: Intended Audience :: Telecommunications Industry
Requires-Python: >=3.6
Requires-Dist: pysimcard
Requires-Dist: pandas
